prothash/__init__.py
prothash/model.py
prothash-0.2.1.dist-info/METADATA
prothash-0.2.1.dist-info/WHEEL
prothash-0.2.1.dist-info/top_level.txt
prothash-0.2.1.dist-info/RECORD
