Metadata-Version: 2.4
Name: prothash
Version: 0.2.1
Summary: A protein language model that outputs amino acid sequence embeddings for use in clustering, classification, locality-sensitive hashing, and more.
Author: Andrew DalPino
License: MIT
Project-URL: Homepage, https://github.com/andrewdalpino/ProtHash
Project-URL: Documentation, https://github.com/andrewdalpino/ProtHash/README.md
Project-URL: Source, https://github.com/andrewdalpino/ProtHash
Requires-Python: >=3.10
Requires-Dist: torch<3.0.0,>=2.7.1
Requires-Dist: torchao<0.13.0,>=0.12.0
Requires-Dist: huggingface_hub<0.34.0,>=0.33.4
Provides-Extra: dev
Requires-Dist: mypy; extra == "dev"
Requires-Dist: black; extra == "dev"
Requires-Dist: matplotlib; extra == "dev"
Provides-Extra: test
Requires-Dist: mypy; extra == "test"
Requires-Dist: black; extra == "test"
